setup.cfg
setup.py
ijson_filter/__init__.py
ijson_filter/__main__.py
ijson_filter/cli.py
ijson_filter/event_filter.py
ijson_filter/ijson-filter
ijson_filter/object_writer.py
ijson_filter.egg-info/PKG-INFO
ijson_filter.egg-info/SOURCES.txt
ijson_filter.egg-info/dependency_links.txt
ijson_filter.egg-info/requires.txt
ijson_filter.egg-info/top_level.txt