Metadata-Version: 1.1
Name: ijson-filter
Version: 1.0
Summary: Iterative JSON filter.
Home-page: https://github.com/rusty-dev/ijson-filter
Author: https://github.com/rusty-dev
Author-email: rustykoc@gmail.com
License: UNKNOWN
Platform: UNKNOWN
Classifier: Development Status :: 4 - Beta
Classifier: Intended Audience :: Developers
Classifier: Natural Language :: English
Classifier: Programming Language :: Python :: 2
Classifier: Programming Language :: Python :: 2.7
Classifier: Programming Language :: Python :: 3
